[
  {
     "signe":"Lion",
     "dateDebut":"23/07",
     "dateFin":"22/08"
  },
  {
     "signe":"Vierge",
     "dateDebut":"23/08",
     "dateFin":"22/09"
  },
  {
     "signe":"Balance",
     "dateDebut":"23/09",
     "dateFin":"23/10"
  },
  {
     "signe":"Scorpion",
     "dateDebut":"24/10",
     "dateFin":"22/11"
  },
  {
     "signe":"Sagittaire",
     "dateDebut":"23/11",
     "dateFin":"22/12"
  },
  {
     "signe":"Capricorne",
     "dateDebut":"23/12",
     "dateFin":"20/01"
  },
  {
     "signe":"Verseau",
     "dateDebut":"21/01",
     "dateFin":"19/02"
  },
  {
     "signe":"Poissons",
     "dateDebut":"20/02",
     "dateFin":"20/03"
  }
]
